{
    "filterOptions": {
        "capabilities": [
            "Speech To Text",
            "Text To Speech",
            "Speech Translation",
            "Realtime Speech To Text",
            "Batch Speech To Text",
            "Batch Text to Speech",
            "Speech Translation",
            "Keyword Recognition",
            "Custom Keyword",
            "Video Translation",
            "Text to Speech Avatar"
        ],
        "languages": [
            "C++",
            "C#",
            "Java",
            "JavaScript",
            "Objective-C",
            "Swift",
            "Python"
        ],
        "platform": [
            "Linux",
            "Windows",
            "IOS",
            "MacOS",
            ".NET Framework",
            ".NET Core",
            "Browser",
            "Node.js",
            "Universal Windows Platform"
        ]
    },
    "samples": [
        {
            "id": "quickstart-recognize-speech-from-a-microphone-python",
            "onboardDate": "2024-09-26",
            "title": "Quickstart: Recognize speech from a microphone from Python using the Speech Service",
            "shortId": "recognize-speech-python",
            "shortDescription": "Demonstrates one-shot speech recognition from a microphone.",
            "fullDescription": "This sample shows how to use the Speech Service through the Speech SDK for Python.",
            "types": [
                "Speech To Text",
                "Realtime Speech To Text"
            ],
            "tags": [
                "Speech To Text",
                "Realtime Speech To Text",
                "Python"
            ],
            "time": "5min to run",
            "configuration": "Ready for debug",
            "thumbnailPath": "https://raw.githubusercontent.com/BinarywoodB/cognitive-services-speech-sdk/extension/vscode_ext/img/realtime-speech-to-text.png",
            "gifPath": "assets/sampleDemo.gif",
            "readmePath": "https://api.github.com/repos/Azure-Samples/cognitive-services-speech-sdk/contents/quickstart/python/from-microphone/README.md",
            "githubPath": "https://github.com/Azure-Samples/cognitive-services-speech-sdk/tree/master/quickstart/python/from-microphone",
            "suggested": true,
            "downloadUrlInfo": {
				"owner": "BinarywoodB",
				"repository": "cognitive-services-speech-sdk",
				"ref": "extension",
				"dir": "quickstart/python/from-microphone"
			}
        },
        {
            "id": "quickstart-recognize-speech-from-a-microphone-cpp-linux",
            "onboardDate": "2024-09-18",
            "title": "Quickstart: Recognize speech from a microphone in C++ using Speech SDK for Linux",
            "shortId": "recognize-speech-cpp-linux",
            "shortDescription": "Demonstrates one-shot speech recognition from a microphone.",
            "fullDescription": "This sample demonstrates how to recognize speech with C++ using the Speech SDK for Linux.",
            "types": [
                "Speech To Text",
                "Realtime Speech To Text"
            ],
            "tags": [
                "Speech To Text",
                "Realtime Speech To Text",
                "C++",
                "Linux"
            ],
            "time": "5min to run",
            "configuration": "Ready for debug",
            "thumbnailPath": "https://raw.githubusercontent.com/BinarywoodB/cognitive-services-speech-sdk/extension/vscode_ext/img/realtime-speech-to-text.png",
            "gifPath": "assets/sampleDemo.gif",
            "readmePath": "https://api.github.com/repos/Azure-Samples/cognitive-services-speech-sdk/contents/quickstart/cpp/linux/from-microphone/README.md",
            "githubPath": "https://github.com/Azure-Samples/cognitive-services-speech-sdk/tree/master/quickstart/cpp/linux/from-microphone",
            "suggested": true,
            "downloadUrlInfo": {
				"owner": "BinarywoodB",
				"repository": "cognitive-services-speech-sdk",
				"ref": "extension",
				"dir": "quickstart/cpp/linux/from-microphone"
			}
        },
        {
            "id": "quickstart-recognize-speech-from-a-microphone-javascript-browser",
            "onboardDate": "2024-09-26",
            "title": "Quickstart: Recognize speech in JavaScript on a Web Browser",
            "shortId": "recognize-speech-javascript-browser",
            "shortDescription": "Demonstrates one-shot speech recognition from a microphone.",
            "fullDescription": "These samples demonstrate how to recognize speech using the Speech SDK for JavaScript on a web browser, like Microsoft Edge, or Chrome.",
            "types": [
                "Speech To Text",
                "Realtime Speech To Text"
            ],
            "tags": [
                "Speech To Text",
                "Realtime Speech To Text",
                "JavaScript",
                "Browser"
            ],
            "time": "5min to run",
            "configuration": "Ready for debug",
            "thumbnailPath": "https://raw.githubusercontent.com/BinarywoodB/cognitive-services-speech-sdk/extension/vscode_ext/img/realtime-speech-to-text.png",
            "gifPath": "assets/sampleDemo.gif",
            "readmePath": "https://api.github.com/repos/Azure-Samples/cognitive-services-speech-sdk/contents/quickstart/javascript/browser/from-microphone/README.md",
            "githubPath": "https://github.com/Azure-Samples/cognitive-services-speech-sdk/tree/master/quickstart/javascript/browser/from-microphone/from-microphone",
            "suggested": true,
            "downloadUrlInfo": {
				"owner": "BinarywoodB",
				"repository": "cognitive-services-speech-sdk",
				"ref": "extension",
				"dir": "quickstart/javascript/browser/from-microphone"
			}
        },
        {
            "id": "quickstart-recognize-speech-from-a-microphone-cpp-windows",
            "onboardDate": "2024-09-18",
            "title": "Quickstart: Recognize speech from a microphone in C++ using Speech SDK for Windows",
            "shortId": "recognize-speech-cpp-windows",
            "shortDescription": "Demonstrates one-shot speech recognition from a microphone.",
            "fullDescription": "This sample demonstrates how to recognize speech with C++ using the Speech SDK for Windows.",
            "types": [
                "Speech To Text",
                "Realtime Speech To Text"
            ],
            "tags": [
                "Speech To Text",
                "Realtime Speech To Text",
                "C++",
                "Windows"
            ],
            "time": "5min to run",
            "configuration": "Ready for debug",
            "thumbnailPath": "https://raw.githubusercontent.com/BinarywoodB/cognitive-services-speech-sdk/extension/vscode_ext/img/realtime-speech-to-text.png",
            "gifPath": "assets/sampleDemo.gif",
            "readmePath": "https://api.github.com/repos/Azure-Samples/cognitive-services-speech-sdk/contents/quickstart/cpp/windows/from-microphone/README.md",
            "githubPath": "https://github.com/Azure-Samples/cognitive-services-speech-sdk/tree/master/quickstart/cpp/windows/from-microphone",
            "suggested": false,
            "downloadUrlInfo": {
				"owner": "Azure-Samples",
				"repository": "cognitive-services-speech-sdk",
				"ref": "master",
				"dir": "quickstart/cpp/windows/from-microphone"
			}
        },
        {
            "id": "quickstart-recognize-speech-from-a-microphone-cpp-macos",
            "onboardDate": "2024-09-18",
            "title": "Quickstart: Recognize speech from a microphone in C++ using Speech SDK for macOS",
            "shortId": "recognize-speech-cpp-macos",
            "shortDescription": "Demonstrates one-shot speech recognition from a microphone.",
            "fullDescription": "This sample demonstrates how to recognize speech with C++ using the Speech SDK for macOS.",
            "types": [
                "Speech To Text",
                "Realtime Speech To Text"
            ],
            "tags": [
                "Speech To Text",
                "Realtime Speech To Text",
                "C++",
                "MacOS"
            ],
            "time": "5min to run",
            "configuration": "Ready for debug",
            "thumbnailPath": "https://raw.githubusercontent.com/BinarywoodB/cognitive-services-speech-sdk/extension/vscode_ext/img/realtime-speech-to-text.png",
            "gifPath": "assets/sampleDemo.gif",
            "readmePath": "https://api.github.com/repos/Azure-Samples/cognitive-services-speech-sdk/contents/quickstart/cpp/macos/from-microphone/README.md",
            "githubPath": "https://github.com/Azure-Samples/cognitive-services-speech-sdk/tree/master/quickstart/cpp/macos/from-microphone",
            "suggested": false,
            "downloadUrlInfo": {
				"owner": "Azure-Samples",
				"repository": "cognitive-services-speech-sdk",
				"ref": "master",
				"dir": "quickstart/cpp/macos/from-microphone"
			}
        },
        {
            "id": "quickstart-recognize-speech-from-a-microphone-csharp-windows",
            "onboardDate": "2024-09-18",
            "title": "Quickstart: Recognize speech from a microphone in C# under .NET Framework for Windows",
            "shortId": "recognize-speech-csharp-windows",
            "shortDescription": "Demonstrates one-shot speech recognition from a microphone.",
            "fullDescription": "This sample demonstrates how to recognize speech  with C# under the .NET Framework (version 4.6.1 or above) using the Speech SDK for Windows.",
            "types": [
                "Speech To Text",
                "Realtime Speech To Text"
            ],
            "tags": [
                "Speech To Text",
                "Realtime Speech To Text",
                "C#",
                "Windows",
                ".NET Framework"
            ],
            "time": "5min to run",
            "configuration": "Ready for debug",
            "thumbnailPath": "https://raw.githubusercontent.com/BinarywoodB/cognitive-services-speech-sdk/extension/vscode_ext/img/realtime-speech-to-text.png",
            "gifPath": "assets/sampleDemo.gif",
            "readmePath": "https://api.github.com/repos/Azure-Samples/cognitive-services-speech-sdk/contents/quickstart/csharp/dotnet/from-microphone/README.md",
            "githubPath": "https://github.com/Azure-Samples/cognitive-services-speech-sdk/tree/master/quickstart/csharp/dotnet/from-microphone",
            "suggested": false,
            "downloadUrlInfo": {
				"owner": "Azure-Samples",
				"repository": "cognitive-services-speech-sdk",
				"ref": "master",
				"dir": "quickstart/csharp/dotnet/from-microphone"
			}
        },
        {
            "id": "quickstart-recognize-speech-from-a-microphone-csharp-dotnetcore",
            "onboardDate": "2024-09-18",
            "title": "Quickstart: Recognize speech from a microphone in C# under .NET 6.0 (Windows, macOS, or Linux)",
            "shortId": "recognize-speech-csharp-dotnetcore",
            "shortDescription": "Demonstrates one-shot speech recognition from a microphone.",
            "fullDescription": "This sample demonstrates how to recognize speech with C# under .NET 6.0 (Windows, macOS, or Linux) using the Speech SDK.",
            "types": [
                "Speech To Text",
                "Realtime Speech To Text"
            ],
            "tags": [
                "Speech To Text",
                "Realtime Speech To Text",
                "C#",
                "Windows",
                "MacOS",
                "Linux",
                ".NET Core"
            ],
            "time": "5min to run",
            "configuration": "Ready for debug",
            "thumbnailPath": "https://raw.githubusercontent.com/BinarywoodB/cognitive-services-speech-sdk/extension/vscode_ext/img/realtime-speech-to-text.png",
            "gifPath": "assets/sampleDemo.gif",
            "readmePath": "https://api.github.com/repos/Azure-Samples/cognitive-services-speech-sdk/contents/quickstart/csharp/dotnetcore/from-microphone/README.md",
            "githubPath": "https://github.com/Azure-Samples/cognitive-services-speech-sdk/tree/master/quickstart/csharp/dotnetcore/from-microphone",
            "suggested": false,
            "downloadUrlInfo": {
				"owner": "Azure-Samples",
				"repository": "cognitive-services-speech-sdk",
				"ref": "master",
				"dir": "quickstart/csharp/dotnetcore/from-microphone"
			}
        },

        {
            "id": "quickstart-recognize-speech-from-a-file-cpp-windows",
            "onboardDate": "2024-09-18",
            "title": "Quickstart: Recognize speech from a file in C++ for Windows",
            "shortId": "recognize-speech-cpp-dotnetcore",
            "shortDescription": "Demonstrates one-shot speech recognition from a wave file.",
            "fullDescription": "This sample demonstrates how to recognize speech using wave file as an input with C++ using the Speech SDK for Windows.",
            "types": [
                "Speech To Text",
                "Realtime Speech To Text"
            ],
            "tags": [
                "Speech To Text",
                "Realtime Speech To Text",
                "C++",
                "Windows"
            ],
            "time": "5min to run",
            "configuration": "Ready for debug",
            "thumbnailPath": "https://raw.githubusercontent.com/BinarywoodB/cognitive-services-speech-sdk/extension/vscode_ext/img/realtime-speech-to-text.png",
            "gifPath": "assets/sampleDemo.gif",
            "readmePath": "https://api.github.com/repos/Azure-Samples/cognitive-services-speech-sdk/contents/quickstart/cpp/windows/from-file/README.md",
            "githubPath": "https://github.com/Azure-Samples/cognitive-services-speech-sdk/tree/master/quickstart/cpp/windows/from-file/from-microphone",
            "suggested": false,
            "downloadUrlInfo": {
				"owner": "Azure-Samples",
				"repository": "cognitive-services-speech-sdk",
				"ref": "master",
				"dir": "quickstart/cpp/windows/from-file"
			}
        },
        {
            "id": "quickstart-recognize-speech-from-a-file-csharp-dotnet",
            "onboardDate": "2024-09-18",
            "title": "Quickstart: Recognize speech from a file in C# under .NET Framework for Windows",
            "shortId": "recognize-speech-csharp-dotnet",
            "shortDescription": "Demonstrates one-shot speech recognition from a wave file.",
            "fullDescription": "This sample demonstrates how to recognize speech from a wave file with C# under the .NET Framework (version 4.6.1 or above) using the Speech SDK for Windows.",
            "types": [
                "Speech To Text",
                "Realtime Speech To Text"
            ],
            "tags": [
                "Speech To Text",
                "Realtime Speech To Text",
                "C#",
                "Windows",
                ".NET Framework"
            ],
            "time": "5min to run",
            "configuration": "Ready for debug",
            "thumbnailPath": "https://raw.githubusercontent.com/BinarywoodB/cognitive-services-speech-sdk/extension/vscode_ext/img/realtime-speech-to-text.png",
            "gifPath": "assets/sampleDemo.gif",
            "readmePath": "https://api.github.com/repos/Azure-Samples/cognitive-services-speech-sdk/contents/quickstart/csharp/dotnet/from-file/README.md",
            "githubPath": "https://github.com/Azure-Samples/cognitive-services-speech-sdk/tree/master/quickstart/csharp/dotnet/from-file/from-microphone",
            "suggested": false,
            "downloadUrlInfo": {
				"owner": "Azure-Samples",
				"repository": "cognitive-services-speech-sdk",
				"ref": "master",
				"dir": "quickstart/csharp/dotnet/from-file"
			}
        },
        {
            "id": "quickstart-recognize-speech-from-a-file-javascript-browser",
            "onboardDate": "2024-09-18",
            "title": "Quickstart: Recognize speech from an audio file in JavaScript on a Web Browser",
            "shortId": "recognize-speech-javascript-browser",
            "shortDescription": "Demonstrates one-shot speech recognition from a wave file.",
            "fullDescription": "This sample demonstrates how to recognize speech from an audio file using the Speech SDK for JavaScript on a web browser, like Microsoft Edge, or Chrome.",
            "types": [
                "Speech To Text",
                "Realtime Speech To Text"
            ],
            "tags": [
                "Speech To Text",
                "Realtime Speech To Text",
                "JavaScript",
                "Browser"
            ],
            "time": "5min to run",
            "configuration": "Ready for debug",
            "thumbnailPath": "https://raw.githubusercontent.com/BinarywoodB/cognitive-services-speech-sdk/extension/vscode_ext/img/realtime-speech-to-text.png",
            "gifPath": "assets/sampleDemo.gif",
            "readmePath": "https://api.github.com/repos/Azure-Samples/cognitive-services-speech-sdk/contents/quickstart/javascript/browser/from-file/README.md",
            "githubPath": "https://github.com/Azure-Samples/cognitive-services-speech-sdk/tree/master/quickstart/javascript/browser/from-file/from-microphone",
            "suggested": false,
            "downloadUrlInfo": {
				"owner": "BinarywoodB",
				"repository": "cognitive-services-speech-sdk",
				"ref": "master",
				"dir": "quickstart/javascript/browser/from-file"
			}
        },
        {
            "id": "batch-transcription-restapi-csharp",
            "onboardDate": "2024-09-18",
            "title": "Batch Transcription API in C#",
            "shortId": "template-batch-transcrpition-csharp",
            "shortDescription": "Demonstrates usage of batch transcription through Rest API.",
            "fullDescription": "This sample demonstrates how to use the Speech Service Batch Transcription API in C#.",
            "types": [
                "Speech To Text",
                "Batch Speech To Text"
            ],
            "tags": [
                "Speech To Text",
                "Batch Speech To Text",
                "C#"
            ],
            "time": "5min to run",
            "configuration": "Ready for debug",
            "thumbnailPath": "https://raw.githubusercontent.com/BinarywoodB/cognitive-services-speech-sdk/extension/vscode_ext/img/batch-speech-to-text.png",
            "gifPath": "assets/sampleDemo.gif", 
            "readmePath": "https://api.github.com/repos/Azure-Samples/cognitive-services-speech-sdk/contents/samples/batch/csharp/README.md",
            "githubPath": "https://github.com/Azure-Samples/cognitive-services-speech-sdk/tree/master/samples/batch/csharp",
            "suggested": false,
            "downloadUrlInfo": {
				"owner": "Azure-Samples",
				"repository": "cognitive-services-speech-sdk",
				"ref": "master",
				"dir": "samples/batch/csharp"
			}
        },
        {
            "id": "batch-transcription-restapi-js",
            "onboardDate": "2024-09-06",
            "title": "Batch Transcription API in Node JS",
            "shortId": "template-batch-transcrpition-js",
            "shortDescription": "Demonstrates usage of batch transcription through Rest API.",
            "fullDescription": "This sample demonstrates how to use the Speech Service Batch Transcription API from Node.js.",
            "types": [
                "Speech To Text",
                "Batch Speech To Text"
            ],
            "tags": [
                "Speech To Text",
                "Batch Speech To Text",
                "JavaScript",
                "Node.js"
            ],
            "time": "5min to run",
            "configuration": "Ready for debug",
            "thumbnailPath": "https://raw.githubusercontent.com/BinarywoodB/cognitive-services-speech-sdk/extension/vscode_ext/img/batch-speech-to-text.png",
            "gifPath": "assets/sampleDemo.gif",
            "readmePath": "https://api.github.com/repos/Azure-Samples/cognitive-services-speech-sdk/contents/samples/batch/js/node/README.md",
            "githubPath": "https://github.com/Azure-Samples/cognitive-services-speech-sdk/tree/master/samples/batch/js/node",
            "suggested": false,
			"downloadUrlInfo": {
				"owner": "Azure-Samples",
				"repository": "cognitive-services-speech-sdk",
				"ref": "master",
				"dir": "samples/batch/js/node"
			}
        },
        {
            "id": "batch-transcription-restapi-python",
            "onboardDate": "2024-09-06",
            "title": "Batch Transcription API in Python",
            "shortId": "template-batch-transcrpition-python",
            "shortDescription": "Demonstrates usage of batch transcription through Rest API.",
            "fullDescription": "This sample demonstrates how to use the Speech Service Batch Transcription API from Python",
            "types": [
                "Speech To Text",
                "Batch Speech To Text"
            ],
            "tags": [
                "Speech To Text",
                "Batch Speech To Text",
                "Python"
            ],
            "time": "5min to run",
            "configuration": "Ready for debug",
            "thumbnailPath": "https://raw.githubusercontent.com/BinarywoodB/cognitive-services-speech-sdk/extension/vscode_ext/img/batch-speech-to-text.png",
            "gifPath": "assets/sampleDemo.gif",
            "readmePath": "https://api.github.com/repos/Azure-Samples/cognitive-services-speech-sdk/contents/samples/batch/python/README.md",
            "githubPath": "https://github.com/Azure-Samples/cognitive-services-speech-sdk/tree/master/samples/batch/python",
            "suggested": true,
			"downloadUrlInfo": {
				"owner": "Azure-Samples",
				"repository": "cognitive-services-speech-sdk",
				"ref": "master",
				"dir": "samples/batch/python"
			}
        },
        {
            "id": "quickstart-synthesize-speech-python",
            "onboardDate": "2024-09-26",
            "title": "Quickstart: Synthesize speech from Python using the Speech Service",
            "shortId": "synthesize-speech-python",
            "shortDescription": "Demonstrates one-shot speech synthesis to the default speaker.",
            "fullDescription": "This sample demonstrates how to synthesize speech with C++ using the Speech SDK for Linux.",
            "types": [
                "Text to Speech"
            ],
            "tags": [
                "Text to Speech",
                "Python"
            ],
            "time": "5min to run",
            "configuration": "Ready for debug",
            "thumbnailPath": "https://raw.githubusercontent.com/BinarywoodB/cognitive-services-speech-sdk/extension/vscode_ext/img/synthesis-speech.png",
            "gifPath": "assets/sampleDemo.gif",
            "readmePath": "https://api.github.com/repos/Azure-Samples/cognitive-services-speech-sdk/contents/quickstart/python/text-to-speech/README.md",
            "githubPath": "https://github.com/Azure-Samples/cognitive-services-speech-sdk/tree/master/quickstart/python/text-to-speech",
            "suggested": true,
			"downloadUrlInfo": {
				"owner": "Azure-Samples",
				"repository": "cognitive-services-speech-sdk",
				"ref": "master",
				"dir": "quickstart/python/text-to-speech"
			}
        },
        {
            "id": "quickstart-synthesize-speech-cpp-linux",
            "onboardDate": "2024-09-18",
            "title": "Quickstart: Synthesize speech in C++ for Linux",
            "shortId": "synthesize-speech-cpp-linux",
            "shortDescription": "Demonstrates one-shot speech synthesis to the default speaker.",
            "fullDescription": "This sample demonstrates how to synthesize speech with C++ using the Speech SDK for Linux.",
            "types": [
                "Text to Speech"
            ],
            "tags": [
                "Text to Speech",
                "C++",
                "Linux"
            ],
            "time": "5min to run",
            "configuration": "Ready for debug",
            "thumbnailPath": "https://raw.githubusercontent.com/BinarywoodB/cognitive-services-speech-sdk/extension/vscode_ext/img/synthesis-speech.png",
            "gifPath": "assets/sampleDemo.gif",
            "readmePath": "https://api.github.com/repos/Azure-Samples/cognitive-services-speech-sdk/contents/quickstart/cpp/linux/text-to-speech/README.md",
            "githubPath": "https://github.com/Azure-Samples/cognitive-services-speech-sdk/tree/master/quickstart/cpp/linux/text-to-speech",
            "suggested": false,
			"downloadUrlInfo": {
				"owner": "Azure-Samples",
				"repository": "cognitive-services-speech-sdk",
				"ref": "master",
				"dir": "quickstart/cpp/linux/text-to-speech"
			}
        },
        {
            "id": "quickstart-synthesize-speech-cpp-windows",
            "onboardDate": "2024-09-18",
            "title": "Quickstart: Synthesize speech in C++ for Windows",
            "shortId": "synthesize-speech-cpp-windows",
            "shortDescription": "Demonstrates one-shot speech synthesis to the default speaker.",
            "fullDescription": "This sample demonstrates how to synthesize speech with C++ using the Speech SDK for Windows.",
            "types": [
                "Text to Speech"
            ],
            "tags": [
                "Text to Speech",
                "C++",
                "Windows"
            ],
            "time": "5min to run",
            "configuration": "Ready for debug",
            "thumbnailPath": "https://raw.githubusercontent.com/BinarywoodB/cognitive-services-speech-sdk/extension/vscode_ext/img/synthesis-speech.png",
            "gifPath": "assets/sampleDemo.gif",
            "readmePath": "https://api.github.com/repos/Azure-Samples/cognitive-services-speech-sdk/contents/quickstart/cpp/windows/text-to-speech/README.md",
            "githubPath": "https://github.com/Azure-Samples/cognitive-services-speech-sdk/tree/master/quickstart/cpp/windows/text-to-speech",
            "suggested": false,
			"downloadUrlInfo": {
				"owner": "Azure-Samples",
				"repository": "cognitive-services-speech-sdk",
				"ref": "master",
				"dir": "quickstart/cpp/windows/text-to-speech"
			}
        },
        {
            "id": "quickstart-synthesize-speech-cpp-macOS",
            "onboardDate": "2024-09-18",
            "title": "Quickstart: Synthesize speech in C++ for macOS",
            "shortId": "synthesize-speech-cpp-macOS",
            "shortDescription": "Demonstrates one-shot speech synthesis to the default speaker.",
            "fullDescription": "This sample demonstrates how to synthesize speech with C++ using the Speech SDK for macOS.",
            "types": [
                "Text to Speech"
            ],
            "tags": [
                "Text to Speech",
                "C++",
                "MacOS"
            ],
            "time": "5min to run",
            "configuration": "Ready for debug",
            "thumbnailPath": "https://raw.githubusercontent.com/BinarywoodB/cognitive-services-speech-sdk/extension/vscode_ext/img/synthesis-speech.png",
            "gifPath": "assets/sampleDemo.gif",
            "readmePath": "https://api.github.com/repos/Azure-Samples/cognitive-services-speech-sdk/contents/quickstart/cpp/macOS/text-to-speech/README.md",
            "githubPath": "https://github.com/Azure-Samples/cognitive-services-speech-sdk/tree/master/quickstart/cpp/macos/text-to-speech",
            "suggested": false,
			"downloadUrlInfo": {
				"owner": "Azure-Samples",
				"repository": "cognitive-services-speech-sdk",
				"ref": "master",
				"dir": "quickstart/cpp/macOS/text-to-speech"
			}
        },
        {
            "id": "quickstart-synthesize-speech-csharp-dotnet",
            "onboardDate": "2024-09-18",
            "title": "Quickstart: Synthesize speech in C# under .NET Framework for Windows",
            "shortId": "synthesize-speech-csharp-dotnet",
            "shortDescription": "Demonstrates one-shot speech synthesis to the default speaker.",
            "fullDescription": "This sample demonstrates how to synthesize speech with C# under the .NET Framework (version 4.6.1 or above) using the Speech SDK for Windows.",
            "types": [
                "Text to Speech"
            ],
            "tags": [
                "Text to Speech",
                "C#",
                "Windows",
                ".NET Framework"
            ],
            "time": "5min to run",
            "configuration": "Ready for debug",
            "thumbnailPath": "https://raw.githubusercontent.com/BinarywoodB/cognitive-services-speech-sdk/extension/vscode_ext/img/synthesis-speech.png",
            "gifPath": "assets/sampleDemo.gif",
            "readmePath": "https://api.github.com/repos/Azure-Samples/cognitive-services-speech-sdk/contents/quickstart/csharp/dotnet/text-to-speech/README.md",
            "githubPath": "https://github.com/Azure-Samples/cognitive-services-speech-sdk/tree/master/quickstart/csharp/dotnet/text-to-speech",
            "suggested": false,
			"downloadUrlInfo": {
				"owner": "Azure-Samples",
				"repository": "cognitive-services-speech-sdk",
				"ref": "master",
				"dir": "quickstart/csharp/dotnet/text-to-speech"
			}
        },
        {
            "id": "quickstart-synthesize-speech-csharp-uwp",
            "onboardDate": "2024-09-18",
            "title": "Quickstart: Synthesize speech in C# under Universal Windows Platform",
            "shortId": "synthesize-speech-csharp-uwp",
            "shortDescription": "Demonstrates one-shot speech synthesis to the default speaker.",
            "fullDescription": "This sample demonstrates how to synthesize speech with C# under the Universal Windows Platform using the Speech SDK. ",
            "types": [
                "Text to Speech"
            ],
            "tags": [
                "Text to Speech",
                "C#",
                "Universal Windows Platform"
            ],
            "time": "5min to run",
            "configuration": "Ready for debug",
            "thumbnailPath": "https://raw.githubusercontent.com/BinarywoodB/cognitive-services-speech-sdk/extension/vscode_ext/img/synthesis-speech.png",
            "gifPath": "assets/sampleDemo.gif",
            "readmePath": "https://api.github.com/repos/Azure-Samples/cognitive-services-speech-sdk/contents/quickstart/csharp/uwp/text-to-speech/README.md",
            "githubPath": "https://github.com/Azure-Samples/cognitive-services-speech-sdk/tree/master/quickstart/csharp/uwp/text-to-speech",
            "suggested": false,
			"downloadUrlInfo": {
				"owner": "Azure-Samples",
				"repository": "cognitive-services-speech-sdk",
				"ref": "master",
				"dir": "quickstart/csharp/uwp/text-to-speech"
			}
        },
        {
            "id": "quickstart-translate-speech-cpp-windows",
            "onboardDate": "2024-09-18",
            "title": "Quickstart: Translate speech in C++ for Windows",
            "shortId": "translate-speech-cpp-windows",
            "shortDescription": "Demonstrates one-shot speech translation/transcription from a microphone.",
            "fullDescription": "This sample demonstrates how to translate speech with C++ using the Speech SDK for Windows.",
            "types": [
                "Speech Translation"
            ],
            "tags": [
                "Speech Translation",
                "C++",
                "Windows"
            ],
            "time": "5min to run",
            "configuration": "Ready for debug",
            "thumbnailPath": "https://raw.githubusercontent.com/BinarywoodB/cognitive-services-speech-sdk/extension/vscode_ext/img/speech-translation.png",
            "gifPath": "assets/sampleDemo.gif",
            "readmePath": "https://api.github.com/repos/Azure-Samples/cognitive-services-speech-sdk/contents/quickstart/cpp/windows/translate-speech-to-text/README.md",
            "githubPath": "https://github.com/Azure-Samples/cognitive-services-speech-sdk/tree/master/quickstart/cpp/windows/translate-speech-to-text",
            "suggested": true,
			"downloadUrlInfo": {
				"owner": "Azure-Samples",
				"repository": "cognitive-services-speech-sdk",
				"ref": "master",
				"dir": "quickstart/cpp/windows/translate-speech-to-text"
			}
        },
        {
            "id": "quickstart-translate-speech-csharp-dotnet",
            "onboardDate": "2024-09-18",
            "title": "Quickstart: Translate speech in C# for .NET Framework for Windows",
            "shortId": "translate-speech-csharp-dotnet",
            "shortDescription": "Demonstrates one-shot speech translation/transcription from a microphone.",
            "fullDescription": "This sample demonstrates how to translate speech with C# under the .NET Framework (version 4.6.1 or above) using the Speech SDK for Windows.",
            "types": [
                "Speech Translation"
            ],
            "tags": [
                "Speech Translation",
                "C#",
                "Windows",
                ".NET Framework"
            ],
            "time": "5min to run",
            "configuration": "Ready for debug",
            "thumbnailPath": "https://raw.githubusercontent.com/BinarywoodB/cognitive-services-speech-sdk/extension/vscode_ext/img/speech-translation.png",
            "gifPath": "assets/sampleDemo.gif",
            "readmePath": "https://api.github.com/repos/Azure-Samples/cognitive-services-speech-sdk/contents/quickstart/csharp/dotnet/translate-speech-to-text/README.md",
            "githubPath": "https://github.com/Azure-Samples/cognitive-services-speech-sdk/tree/master/quickstart/csharp/dotnet/translate-speech-to-text",
            "suggested": false,
			"downloadUrlInfo": {
				"owner": "Azure-Samples",
				"repository": "cognitive-services-speech-sdk",
				"ref": "master",
				"dir": "quickstart/csharp/dotnet/translate-speech-to-text"
			}
        },
        {
            "id": "quickstart-translate-speech-csharp-dotnetcore",
            "onboardDate": "2024-09-18",
            "title": "Quickstart: Translate speech in C# for .NET Core on Windows or Linux",
            "shortId": "translate-speech-csharp-dotnetcore",
            "shortDescription": "Demonstrates one-shot speech translation/transcription from a microphone.",
            "fullDescription": "This sample demonstrates how to translate speech with C# under .NET 6.0 (Windows or Linux) using the Speech SDK.",
            "types": [
                "Speech Translation"
            ],
            "tags": [
                "Speech Translation",
                "C#",
                "Windows",
                "Linux",
                ".NET Core"
            ],
            "time": "5min to run",
            "configuration": "Ready for debug",
            "thumbnailPath": "https://raw.githubusercontent.com/BinarywoodB/cognitive-services-speech-sdk/extension/vscode_ext/img/speech-translation.png",
            "gifPath": "assets/sampleDemo.gif",
            "readmePath": "https://api.github.com/repos/Azure-Samples/cognitive-services-speech-sdk/contents/quickstart/csharp/dotnetcore/translate-speech-to-text/README.md",
            "githubPath": "https://github.com/Azure-Samples/cognitive-services-speech-sdk/tree/master/quickstart/csharp/dotnetcore/translate-speech-to-text",
            "suggested": false,
			"downloadUrlInfo": {
				"owner": "Azure-Samples",
				"repository": "cognitive-services-speech-sdk",
				"ref": "master",
				"dir": "quickstart/csharp/dotnetcore/translate-speech-to-text"
			}
        },
        {
            "id": "quickstart-translate-speech-csharp-uwp",
            "onboardDate": "2024-09-18",
            "title": "Quickstart: Translate speech from a microphone in C# for Universal Windows Platform",
            "shortId": "translate-speech-csharp-uwp",
            "shortDescription": "Demonstrates one-shot speech translation/transcription from a microphone.",
            "fullDescription": "This sample demonstrates how to translate speech with C# under the Universal Windows Platform using the Speech SDK.",
            "types": [
                "Speech Translation"
            ],
            "tags": [
                "Speech Translation",
                "C#",
                "Universal Windows Platform"
            ],
            "time": "5min to run",
            "configuration": "Ready for debug",
            "thumbnailPath": "https://raw.githubusercontent.com/BinarywoodB/cognitive-services-speech-sdk/extension/vscode_ext/img/speech-translation.png",
            "gifPath": "assets/sampleDemo.gif",
            "readmePath": "https://api.github.com/repos/Azure-Samples/cognitive-services-speech-sdk/contents/quickstart/csharp/uwp/translate-speech-to-text/README.md",
            "githubPath": "https://github.com/Azure-Samples/cognitive-services-speech-sdk/tree/master/quickstart/csharp/uwp/translate-speech-to-text",
            "suggested": false,
			"downloadUrlInfo": {
				"owner": "Azure-Samples",
				"repository": "cognitive-services-speech-sdk",
				"ref": "master",
				"dir": "quickstart/csharp/uwp/translate-speech-to-text"
			}
        },
        {
            "id": "quickstart-translate-speech-java-jre",
            "onboardDate": "2024-09-18",
            "title": "Quickstart: Translate speech in Java on Windows, macOS or Linux",
            "shortId": "translate-speech-java-jre",
            "shortDescription": "Demonstrates one-shot speech translation/transcription from a microphone.",
            "fullDescription": "This sample demonstrates how to translate speech with the Speech SDK for Java on Windows, macOS or Linux.",
            "types": [
                "Speech Translation"
            ],
            "tags": [
                "Speech Translation",
                "Java",
                "Windows",
                "Linux",
                "MacOS"
            ],
            "time": "5min to run",
            "configuration": "Ready for debug",
            "thumbnailPath": "https://raw.githubusercontent.com/BinarywoodB/cognitive-services-speech-sdk/extension/vscode_ext/img/speech-translation.png",
            "gifPath": "assets/sampleDemo.gif",
            "readmePath": "https://api.github.com/repos/Azure-Samples/cognitive-services-speech-sdk/contents/quickstart/java/jre/translate-speech-to-text/README.md",
            "githubPath": "https://github.com/Azure-Samples/cognitive-services-speech-sdk/tree/master/quickstart/java/jre/translate-speech-to-text",
            "suggested": false,
			"downloadUrlInfo": {
				"owner": "Azure-Samples",
				"repository": "cognitive-services-speech-sdk",
				"ref": "master",
				"dir": "quickstart/java/jre/translate-speech-to-text"
			}
        },
        {
            "id": "samples-recognize-speech-in-compressed-audio-input-stream-cpp-linux",
            "onboardDate": "2024-09-18",
            "title": "Sample: Recognize speech in C++ for Linux from an MP3/Opus file",
            "shortId": "recognize-speech-in-compressed-audio-input-stream-cpp-linux",
            "shortDescription": "Demonstrates speech recognition from an MP3/Opus file",
            "fullDescription": "This sample demonstrates how to recognize speech in compressed audio input stream with C++ using the Speech SDK for Linux.",
            "types": [
                "Speech To Text",
                "Realtime Speech To Text"
            ],
            "tags": [
                "Speech To Text",
                "Realtime Speech To Text",
                "C++",
                "Linux"
            ],
            "time": "5min to run",
            "configuration": "Ready for debug",
            "thumbnailPath": "https://raw.githubusercontent.com/BinarywoodB/cognitive-services-speech-sdk/extension/vscode_ext/img/realtime-speech-to-text.png",
            "gifPath": "assets/sampleDemo.gif",
            "readmePath": "https://api.github.com/repos/Azure-Samples/cognitive-services-speech-sdk/contents/samples/cpp/linux/compressed-audio-input/README.md",
            "githubPath": "https://github.com/Azure-Samples/cognitive-services-speech-sdk/tree/master/samples/cpp/linux/compressed-audio-input",
            "suggested": false,
			"downloadUrlInfo": {
				"owner": "Azure-Samples",
				"repository": "cognitive-services-speech-sdk",
				"ref": "master",
				"dir": "samples/cpp/linux/compressed-audio-input"
			}
        },
        {
            "id": "quickstart-recognize-keywords-csharp-uwp",
            "onboardDate": "2024-09-18",
            "title": "Quickstart: Recognize keywords in C# under Universal Windows Platform",
            "shortId": "recognize-keywords-csharp-uwp",
            "shortDescription": "Demonstrates speech recognition from an MP3/Opus file",
            "fullDescription": "This sample demonstrates how to recognize keywords with C# under the Universal Windows Platform using the Speech SDK.",
            "types": [
                "Keyword Recognition",
                "Custom Keyword"
            ],
            "tags": [
                "Keyword Recognition",
                "Custom Keyword",
                "C++",
                "Linux"
            ],
            "time": "5min to run",
            "configuration": "Ready for debug",
            "thumbnailPath": "https://raw.githubusercontent.com/BinarywoodB/cognitive-services-speech-sdk/extension/vscode_ext/img/custom-keyword.png",
            "gifPath": "assets/sampleDemo.gif",
            "readmePath": "https://api.github.com/repos/Azure-Samples/cognitive-services-speech-sdk/contents/quickstart/csharp/uwp/keyword-recognizer/README.md",
            "githubPath": "https://github.com/Azure-Samples/cognitive-services-speech-sdk/tree/master/quickstart/csharp/uwp/keyword-recognizer",
            "suggested": false,
			"downloadUrlInfo": {
				"owner": "Azure-Samples",
				"repository": "cognitive-services-speech-sdk",
				"ref": "master",
				"dir": "quickstart/csharp/uwp/keyword-recognizer"
			}
        },
        {
            "id": "sample-video-translation-csharp-windows",
            "onboardDate": "2024-09-18",
            "title": "Video Translation (REST API) C#",
            "shortId": "video-translation-csharp-windows",
            "shortDescription": "Demonstrates video translation API",
            "fullDescription": "This sample demonstrates how to use the Speech Service Video Translation API in C# on Windows.",
            "types": [
                "Video Translation"
            ],
            "tags": [
                "Video Translation",
                "C#",
                "Windows"
            ],
            "time": "5min to run",
            "configuration": "Ready for debug",
            "thumbnailPath": "https://raw.githubusercontent.com/BinarywoodB/cognitive-services-speech-sdk/extension/vscode_ext/img/video-translation.png",
            "gifPath": "assets/sampleDemo.gif",
            "readmePath": "https://api.github.com/repos/Azure-Samples/cognitive-services-speech-sdk/contents/samples/video-translation/csharp/README.md",
            "githubPath": "https://github.com/Azure-Samples/cognitive-services-speech-sdk/tree/master/samples/video-translation/csharp",
            "suggested": false,
			"downloadUrlInfo": {
				"owner": "Azure-Samples",
				"repository": "cognitive-services-speech-sdk",
				"ref": "master",
				"dir": "samples/video-translation/csharp"
			}
        },
        {
            "id": "sample-batch-avatar-csharp",
            "onboardDate": "2024-09-18",
            "title": "Batch Avatar Synthesis (REST API) C#",
            "shortId": "batch-avatar-csharp",
            "shortDescription": "Demonstrates batch avatar API",
            "fullDescription": "The Batch avatar synthesis API (Preview) provides asynchronous synthesis of talking avatar to generate avatar video content with the text input.",
            "types": [
                "Text to Speech Avatar"
            ],
            "tags": [
                "Text to Speech Avatar",
                "C#"
            ],
            "time": "5min to run",
            "configuration": "Ready for debug",
            "thumbnailPath": "https://raw.githubusercontent.com/BinarywoodB/cognitive-services-speech-sdk/extension/vscode_ext/img/batch-avatar.png",
            "gifPath": "assets/sampleDemo.gif",
            "readmePath": "https://api.github.com/repos/Azure-Samples/cognitive-services-speech-sdk/contents/samples/batch-avatar/README.md",
            "githubPath": "https://github.com/Azure-Samples/cognitive-services-speech-sdk/tree/master/samples/batch-avatar/",
            "suggested": false,
			"downloadUrlInfo": {
				"owner": "Azure-Samples",
				"repository": "cognitive-services-speech-sdk",
				"ref": "master",
				"dir": "samples/batch-avatar/csharp/BatchAvatarSample"
			}
        },
        {
            "id": "sample-batch-avatar-python",
            "onboardDate": "2024-09-18",
            "title": "Batch Avatar Synthesis (REST API) Python",
            "shortId": "batch-avatar-python",
            "shortDescription": "Demonstrates batch avatar API",
            "fullDescription": "The Batch avatar synthesis API (Preview) provides asynchronous synthesis of talking avatar to generate avatar video content with the text input.",
            "types": [
                "Text to Speech Avatar"
            ],
            "tags": [
                "Text to Speech Avatar",
                "Python"
            ],
            "time": "5min to run",
            "configuration": "Ready for debug",
            "thumbnailPath": "https://raw.githubusercontent.com/BinarywoodB/cognitive-services-speech-sdk/extension/vscode_ext/img/batch-avatar.png",
            "gifPath": "assets/sampleDemo.gif",
            "readmePath": "https://api.github.com/repos/Azure-Samples/cognitive-services-speech-sdk/contents/samples/batch-avatar/python/README.md",
            "githubPath": "https://github.com/Azure-Samples/cognitive-services-speech-sdk/tree/master/samples/batch-avatar/python/",
            "suggested": false,
			"downloadUrlInfo": {
				"owner": "Azure-Samples",
				"repository": "cognitive-services-speech-sdk",
				"ref": "master",
				"dir": "samples/batch-avatar/python"
			}
        },
        {
            "id": "sample-batch-synthesis-csharp",
            "onboardDate": "2024-09-18",
            "title": "Batch Synthesis (REST API) C#",
            "shortId": "batch-synthesis-csharp",
            "shortDescription": "Demonstrates batch synthesis API",
            "fullDescription": "The Batch synthesis API provides asynchronous synthesis of long-form text to speech.",
            "types": [
                "Text to Speech",
                "Batch Text to Speech"
            ],
            "tags": [
                "Text to Speech",
                "Batch Text to Speech",
                "C#"
            ],
            "time": "5min to run",
            "configuration": "Ready for debug",
            "thumbnailPath": "https://raw.githubusercontent.com/BinarywoodB/cognitive-services-speech-sdk/extension/vscode_ext/img/synthesis-speech.png",
            "gifPath": "assets/sampleDemo.gif",
            "readmePath": "https://api.github.com/repos/Azure-Samples/cognitive-services-speech-sdk/contents/samples/batch-synthesis/README.md",
            "githubPath": "https://github.com/Azure-Samples/cognitive-services-speech-sdk/tree/master/samples/batch-synthesis",
            "suggested": false,
			"downloadUrlInfo": {
				"owner": "Azure-Samples",
				"repository": "cognitive-services-speech-sdk",
				"ref": "master",
				"dir": "samples/batch-synthesis/csharp"
			}
        },
        {
            "id": "sample-batch-synthesis-python",
            "onboardDate": "2024-09-18",
            "title": "Batch Synthesis (REST API) Python",
            "shortId": "batch-synthesis-python",
            "shortDescription": "Demonstrates batch synthesis API",
            "fullDescription": "The Batch synthesis API provides asynchronous synthesis of long-form text to speech.",
            "types": [
                "Text to Speech",
                "Batch Text to Speech"
            ],
            "tags": [
                "Text to Speech",
                "Batch Text to Speech",
                "Python"
            ],
            "time": "5min to run",
            "configuration": "Ready for debug",
            "thumbnailPath": "https://raw.githubusercontent.com/BinarywoodB/cognitive-services-speech-sdk/extension/vscode_ext/img/synthesis-speech.png",
            "gifPath": "assets/sampleDemo.gif",
            "readmePath": "https://api.github.com/repos/Azure-Samples/cognitive-services-speech-sdk/contents/samples/batch-synthesis/README.md",
            "githubPath": "https://github.com/Azure-Samples/cognitive-services-speech-sdk/tree/master/samples/batch-synthesis",
            "suggested": false,
			"downloadUrlInfo": {
				"owner": "Azure-Samples",
				"repository": "cognitive-services-speech-sdk",
				"ref": "master",
				"dir": "samples/batch-synthesis/python"
			}
        }
    ]
}